keynote_parser/__init__.py
keynote_parser/bundle_utils.py
keynote_parser/codec.py
keynote_parser/command_line.py
keynote_parser/file_utils.py
keynote_parser/macos_app_version.py
keynote_parser/mapping.py
keynote_parser/replacement.py
keynote_parser/unicode_utils.py
keynote_parser/generated/KNArchives_pb2.py
keynote_parser/generated/KNArchives_sos_pb2.py
keynote_parser/generated/KNCommandArchives_pb2.py
keynote_parser/generated/KNCommandArchives_sos_pb2.py
keynote_parser/generated/TSAArchives_pb2.py
keynote_parser/generated/TSAArchives_sos_pb2.py
keynote_parser/generated/TSACommandArchives_sos_pb2.py
keynote_parser/generated/TSCEArchives_pb2.py
keynote_parser/generated/TSCH3DArchives_pb2.py
keynote_parser/generated/TSCHArchives_Common_pb2.py
keynote_parser/generated/TSCHArchives_GEN_pb2.py
keynote_parser/generated/TSCHArchives_pb2.py
keynote_parser/generated/TSCHArchives_sos_pb2.py
keynote_parser/generated/TSCHCommandArchives_pb2.py
keynote_parser/generated/TSCHPreUFFArchives_pb2.py
keynote_parser/generated/TSCKArchives_pb2.py
keynote_parser/generated/TSCKArchives_sos_pb2.py
keynote_parser/generated/TSDArchives_pb2.py
keynote_parser/generated/TSDArchives_sos_pb2.py
keynote_parser/generated/TSDCommandArchives_pb2.py
keynote_parser/generated/TSKArchives_pb2.py
keynote_parser/generated/TSKArchives_sos_pb2.py
keynote_parser/generated/TSPArchiveMessages_pb2.py
keynote_parser/generated/TSPDatabaseMessages_pb2.py
keynote_parser/generated/TSPMessages_pb2.py
keynote_parser/generated/TSSArchives_pb2.py
keynote_parser/generated/TSSArchives_sos_pb2.py
keynote_parser/generated/TSTArchives_pb2.py
keynote_parser/generated/TSTArchives_sos_pb2.py
keynote_parser/generated/TSTCommandArchives_pb2.py
keynote_parser/generated/TSTStylePropertyArchiving_pb2.py
keynote_parser/generated/TSWPArchives_pb2.py
keynote_parser/generated/TSWPArchives_sos_pb2.py
keynote_parser/generated/TSWPCommandArchives_pb2.py
keynote_parser/generated/__init__.py
keynote_parser-1.14.4.0.dist-info/METADATA
keynote_parser-1.14.4.0.dist-info/WHEEL
keynote_parser-1.14.4.0.dist-info/entry_points.txt
keynote_parser-1.14.4.0.dist-info/top_level.txt
keynote_parser-1.14.4.0.dist-info/RECORD
