Metadata-Version: 2.4
Name: keynote-parser
Version: 1.14.4.0
Summary: A tool for manipulating Apple Keynote presentation files.
Home-page: https://github.com/psobot/keynote-parser
Author: Peter Sobot
Author-email: github@petersobot.com
Project-URL: Bug Reports, https://github.com/psobot/keynote-parser/issues
Project-URL: Source, https://github.com/psobot/keynote-parser/
Keywords: keynote macOS apple presentation powerpoint
Classifier: Development Status :: 4 - Beta
Classifier: Intended Audience :: Developers
Classifier: Topic :: Software Development :: Build Tools
Classifier: License :: OSI Approved :: MIT License
Classifier: Programming Language :: Python :: 3
Classifier: Programming Language :: Python :: 3.9
Classifier: Programming Language :: Python :: 3.10
Classifier: Programming Language :: Python :: 3.11
Classifier: Programming Language :: Python :: 3.12
Classifier: Programming Language :: Python :: 3.13
Requires-Dist: protobuf>=3.13.0
Requires-Dist: tqdm>=4.14.0
Requires-Dist: python-snappy>=0.5.3
Requires-Dist: PyYAML>=5.3.1
Requires-Dist: Pillow>=7.1.0
Requires-Dist: future>=0.17.1
Requires-Dist: colorama>=0.4.3
Provides-Extra: dev
Requires-Dist: check-manifest; extra == "dev"
Provides-Extra: test
Requires-Dist: coverage; extra == "test"
Dynamic: author
Dynamic: author-email
Dynamic: classifier
Dynamic: description
Dynamic: description-content-type
Dynamic: home-page
Dynamic: keywords
Dynamic: project-url
Dynamic: provides-extra
Dynamic: requires-dist
Dynamic: summary
